.gitignore
README.rst
setup.py
data/sfr_Behroozi.dat
data/sfr_processed_TNG100-1.npz
data/sfr_processed_TNG300-1.npz
limpy/__init__.py
limpy/analysis.py
limpy/cosmos.py
limpy/inputs.py
limpy/lines.py
limpy/params.py
limpy/plotsettings.py
limpy/powerspectra.py
limpy/theory.py
limpy/utils.py
limpy.egg-info/PKG-INFO
limpy.egg-info/SOURCES.txt
limpy.egg-info/dependency_links.txt
limpy.egg-info/not-zip-safe
limpy.egg-info/requires.txt
limpy.egg-info/top_level.txt