Metadata-Version: 2.1
Name: limpy
Version: 1.0
Summary: Line Intensity Mapping code in PYthon
Author: Anirban Roy
Author-email: anirbanroy.personal@gmail.com
